pycoreux/__init__.py
pycoreux/archive_utils.py
pycoreux/file_ops.py
pycoreux/path_utils.py
pycoreux/process_utils.py
pycoreux/text_utils.py
pycoreux-0.1.1.dist-info/licenses/LICENSE
pycoreux-0.1.1.dist-info/METADATA
pycoreux-0.1.1.dist-info/WHEEL
pycoreux-0.1.1.dist-info/top_level.txt
pycoreux-0.1.1.dist-info/RECORD
