Metadata-Version: 2.4
Name: pycoreux
Version: 0.1.1
Summary: A Python library providing shell-like utilities for file operations, text processing, and subprocess management
Author-email: Munish Kumar <munishkumar631@gmail.com>
License: MIT
Project-URL: Homepage, https://github.com/kumarmunish/pycoreux
Project-URL: Repository, https://github.com/kumarmunish/pycoreux
Project-URL: Issues, https://github.com/kumarmunish/pycoreux/issues
Keywords: shell,utilities,coreutils,file-processing,text-processing
Classifier: Development Status :: 3 - Alpha
Classifier: Intended Audience :: Developers
Classifier: License :: OSI Approved :: MIT License
Classifier: Operating System :: OS Independent
Classifier: Programming Language :: Python :: 3
Classifier: Programming Language :: Python :: 3.8
Classifier: Programming Language :: Python :: 3.9
Classifier: Programming Language :: Python :: 3.10
Classifier: Programming Language :: Python :: 3.11
Classifier: Programming Language :: Python :: 3.12
Classifier: Programming Language :: Python :: 3.12
Classifier: Topic :: Software Development :: Libraries :: Python Modules
Classifier: Topic :: System :: Shells
Classifier: Topic :: Text Processing
Classifier: Topic :: Utilities
Requires-Python: >=3.8
License-File: LICENSE
Provides-Extra: dev
Requires-Dist: pytest>=7.0; extra == "dev"
Requires-Dist: pytest-cov>=4.0; extra == "dev"
Requires-Dist: black>=23.0; extra == "dev"
Requires-Dist: isort>=5.0; extra == "dev"
Requires-Dist: mypy>=1.0; extra == "dev"
Requires-Dist: flake8>=6.0; extra == "dev"
Requires-Dist: pre-commit>=3.0; extra == "dev"
Requires-Dist: build>=0.10.0; extra == "dev"
Requires-Dist: twine>=4.0.0; extra == "dev"
Provides-Extra: enhanced
Requires-Dist: psutil>=5.0; extra == "enhanced"
Dynamic: license-file
